{"name":"build-javascript","namedChunkGroups":{"polyfill":{"name":"polyfill","assets":[{"name":"webpack-runtime-734f1f61d3c8cbb9d33d.js","size":4995},{"name":"polyfill-28dbfa58150ea9910781.js","size":85836}],"filteredAssets":0,"assetsSize":90831,"filteredAuxiliaryAssets":2,"auxiliaryAssetsSize":227856},"app":{"name":"app","assets":[{"name":"webpack-runtime-734f1f61d3c8cbb9d33d.js","size":4995},{"name":"framework-deb5402af5b406c6372a.js","size":129749},{"name":"app-1fec35251692f9c33161.js","size":70282}],"filteredAssets":0,"assetsSize":205026,"filteredAuxiliaryAssets":3,"auxiliaryAssetsSize":662456},"component---src-pages-404-js":{"name":"component---src-pages-404-js","assets":[{"name":"styles.2dddc37d2eb521a9a913.css","size":2898434},{"name":"1bfc9850-dec4be7fe954efecc37b.js","size":3502},{"name":"commons-73f451cc247cdc3049ed.js","size":18487},{"name":"component---src-pages-404-js-52a62563bdbf22f9fd77.js","size":11750}],"filteredAssets":0,"assetsSize":2932173,"filteredAuxiliaryAssets":3,"auxiliaryAssetsSize":1614856},"component---src-pages-index-js":{"name":"component---src-pages-index-js","assets":[{"name":"styles.2dddc37d2eb521a9a913.css","size":2898434},{"name":"1bfc9850-dec4be7fe954efecc37b.js","size":3502},{"name":"commons-73f451cc247cdc3049ed.js","size":18487},{"name":"component---src-pages-index-js-da3715e763343188ecf6.js","size":73636}],"filteredAssets":0,"assetsSize":2994059,"filteredAuxiliaryAssets":3,"auxiliaryAssetsSize":1904048}},"assetsByChunkName":{"polyfill":["webpack-runtime-734f1f61d3c8cbb9d33d.js","polyfill-28dbfa58150ea9910781.js"],"app":["webpack-runtime-734f1f61d3c8cbb9d33d.js","framework-deb5402af5b406c6372a.js","app-1fec35251692f9c33161.js"],"component---src-pages-404-js":["styles.2dddc37d2eb521a9a913.css","1bfc9850-dec4be7fe954efecc37b.js","commons-73f451cc247cdc3049ed.js","component---src-pages-404-js-52a62563bdbf22f9fd77.js"],"component---src-pages-index-js":["styles.2dddc37d2eb521a9a913.css","1bfc9850-dec4be7fe954efecc37b.js","commons-73f451cc247cdc3049ed.js","component---src-pages-index-js-da3715e763343188ecf6.js"]},"childAssetsByChunkName":{}}